llama_index/multi_modal_llms/mistralai/__init__.py
llama_index/multi_modal_llms/mistralai/base.py
llama_index/multi_modal_llms/mistralai/utils.py
llama_index_multi_modal_llms_mistral-0.1.dist-info/METADATA
llama_index_multi_modal_llms_mistral-0.1.dist-info/WHEEL
llama_index_multi_modal_llms_mistral-0.1.dist-info/RECORD
