Metadata-Version: 2.1
Name: llama-index-multi-modal-llms-mistral
Version: 0.1
Summary: llama-index multi-modal-llms mistral integration
License: MIT
Author: Your Name
Author-email: you@example.com
Requires-Python: >=3.9,<4.0
Classifier: License :: OSI Approved :: MIT License
Classifier: Programming Language :: Python :: 3
Classifier: Programming Language :: Python :: 3.9
Classifier: Programming Language :: Python :: 3.10
Classifier: Programming Language :: Python :: 3.11
Classifier: Programming Language :: Python :: 3.12
Requires-Dist: filetype (>=1.2.0,<2.0.0)
Requires-Dist: llama-index-core (>=0.11.0,<0.12.0)
Requires-Dist: mistralai (>=1.1.0)
